pepper8/__init__.py
pepper8/generator.py
pepper8/main.py
pepper8/models.py
pepper8/parser.py
pepper8/templates/base.html
pepper8-1.1.1.dist-info/DESCRIPTION.rst
pepper8-1.1.1.dist-info/METADATA
pepper8-1.1.1.dist-info/RECORD
pepper8-1.1.1.dist-info/WHEEL
pepper8-1.1.1.dist-info/entry_points.txt
pepper8-1.1.1.dist-info/metadata.json
pepper8-1.1.1.dist-info/top_level.txt
