Metadata-Version: 2.0
Name: pepper8
Version: 1.1.1
Summary: Transforms pep8 or flake8 output into an HTML report.
Home-page: https://github.com/myth/pepper8
Author: Aleksander 'myth' Skraastad'
Author-email: myth@overflow.no
License: MIT License
Platform: UNKNOWN
Classifier: Intended Audience :: Developers
Classifier: Topic :: Software Development :: Build Tools
Classifier: Natural Language :: English
Classifier: Programming Language :: Python :: 2.7
Classifier: Programming Language :: Python :: 3
Classifier: Programming Language :: Python :: 3.4
Classifier: Programming Language :: Python :: 3.5
Requires-Dist: Jinja2 (>=2.7)
